faucetconfrpc/__init__.py
faucetconfrpc/faucetconfrpc_client.py
faucetconfrpc/faucetconfrpc_client_lib.py
faucetconfrpc/faucetconfrpc_pb2.py
faucetconfrpc/faucetconfrpc_pb2_grpc.py
faucetconfrpc/faucetconfrpc_server.py
faucetconfrpc/generate_pb_grpc.sh
faucetconfrpc/protos/faucetconfrpc/faucetconfrpc.proto
faucetconfrpc-0.55.78.dist-info/METADATA
faucetconfrpc-0.55.78.dist-info/WHEEL
faucetconfrpc-0.55.78.dist-info/entry_points.txt
faucetconfrpc-0.55.78.dist-info/licenses/LICENSE
faucetconfrpc-0.55.78.dist-info/RECORD
