Metadata-Version: 2.4
Name: faucetconfrpc
Version: 0.55.78
Summary: utility to manage FAUCET config files via RPC
License: Apache-2.0
License-File: LICENSE
Author: Charlie Lewis
Author-email: clewis@iqt.org
Requires-Python: >=3.11,<3.14
Classifier: License :: OSI Approved :: Apache Software License
Classifier: Programming Language :: Python :: 3
Classifier: Programming Language :: Python :: 3.11
Classifier: Programming Language :: Python :: 3.12
Classifier: Programming Language :: Python :: 3.13
Requires-Dist: c65faucet (==1.0.96)
Requires-Dist: cryptography (==46.0.3)
Requires-Dist: dnspython (<2.8.1)
Requires-Dist: grpcio (==1.76.0)
Requires-Dist: grpcio-tools (==1.76.0)
Requires-Dist: os-ken (>=3.0.1)
Requires-Dist: prometheus_client (==0.23.1)
Requires-Dist: protobuf (==6.33.2)
Requires-Dist: pybind11 (==3.0.1)
Requires-Dist: pyopenssl (>22.1.0)
Project-URL: homepage, https://github.com/IQTLabs/faucetconfrpc
